twoNeuron/__init__.py
twoNeuron/perceptron.py
twoNeuron_pypi_chittariraghu-0.0.2.dist-info/LICENSE
twoNeuron_pypi_chittariraghu-0.0.2.dist-info/METADATA
twoNeuron_pypi_chittariraghu-0.0.2.dist-info/WHEEL
twoNeuron_pypi_chittariraghu-0.0.2.dist-info/top_level.txt
twoNeuron_pypi_chittariraghu-0.0.2.dist-info/RECORD
