Metadata-Version: 2.1
Name: twoNeuron-pypi-chittariraghu
Version: 0.0.2
Summary: its an implimentation of Perceptron
Home-page: https://github.com/chittariraghu/twoNeuron_pypi
Author: chittariraghu
Author-email: chittariraghu@gmail.com
License: UNKNOWN
Project-URL: Bug Tracker, https://github.com/chittariraghu/twoNeuron_pypi/issues
Platform: UNKNOWN
Classifier: Programming Language :: Python :: 3
Classifier: License :: OSI Approved :: MIT License
Classifier: Operating System :: OS Independent
Requires-Python: >=3.7
License-File: LICENSE
Requires-Dist: numpy
Requires-Dist: tqdm
